setup.py
apasvenskas.egg-info/PKG-INFO
apasvenskas.egg-info/SOURCES.txt
apasvenskas.egg-info/dependency_links.txt
apasvenskas.egg-info/requires.txt
apasvenskas.egg-info/top_level.txt
invoicing/__init__.py
invoicing/invoice.py